fastybird_fb_mqtt_connector/__init__.py
fastybird_fb_mqtt_connector/bootstrap.py
fastybird_fb_mqtt_connector/connector.py
fastybird_fb_mqtt_connector/entities.py
fastybird_fb_mqtt_connector/exceptions.py
fastybird_fb_mqtt_connector/logger.py
fastybird_fb_mqtt_connector/py.typed
fastybird_fb_mqtt_connector/types.py
fastybird_fb_mqtt_connector/api/__init__.py
fastybird_fb_mqtt_connector/api/v1builder.py
fastybird_fb_mqtt_connector/api/v1parser.py
fastybird_fb_mqtt_connector/api/v1validator.py
fastybird_fb_mqtt_connector/clients/__init__.py
fastybird_fb_mqtt_connector/clients/apiv1.py
fastybird_fb_mqtt_connector/clients/client.py
fastybird_fb_mqtt_connector/consumers/__init__.py
fastybird_fb_mqtt_connector/consumers/channel.py
fastybird_fb_mqtt_connector/consumers/consumer.py
fastybird_fb_mqtt_connector/consumers/device.py
fastybird_fb_mqtt_connector/consumers/entities.py
fastybird_fb_mqtt_connector/consumers/extension.py
fastybird_fb_mqtt_connector/consumers/property.py
fastybird_fb_mqtt_connector/events/__init__.py
fastybird_fb_mqtt_connector/events/events.py
fastybird_fb_mqtt_connector/events/listeners.py
fastybird_fb_mqtt_connector/registry/__init__.py
fastybird_fb_mqtt_connector/registry/model.py
fastybird_fb_mqtt_connector/registry/records.py
fastybird_fb_mqtt_connector/subscriptions/__init__.py
fastybird_fb_mqtt_connector/subscriptions/entities.py
fastybird_fb_mqtt_connector/subscriptions/repository.py
tests/__init__.py
tests/pytests/__init__.py
fastybird_fb_mqtt_connector-0.24.0.dist-info/LICENSE.md
fastybird_fb_mqtt_connector-0.24.0.dist-info/METADATA
fastybird_fb_mqtt_connector-0.24.0.dist-info/WHEEL
fastybird_fb_mqtt_connector-0.24.0.dist-info/top_level.txt
fastybird_fb_mqtt_connector-0.24.0.dist-info/RECORD
